faststripe/__init__.py
faststripe/_modidx.py
faststripe/core.py
faststripe/endpoints.py
faststripe/page.py
faststripe/spec.py
faststripe-2025.11.17.1.dist-info/licenses/LICENSE
faststripe-2025.11.17.1.dist-info/METADATA
faststripe-2025.11.17.1.dist-info/WHEEL
faststripe-2025.11.17.1.dist-info/entry_points.txt
faststripe-2025.11.17.1.dist-info/top_level.txt
faststripe-2025.11.17.1.dist-info/RECORD
